kamoe_lstm/__init__.py
kamoe_lstm/grkan.py
kamoe_lstm/kamoe.py
kamoe_lstm/kan.py
kamoe_lstm-0.1.4.dist-info/METADATA
kamoe_lstm-0.1.4.dist-info/WHEEL
kamoe_lstm-0.1.4.dist-info/RECORD
