Metadata-Version: 2.1
Name: kamoe_lstm
Version: 0.1.4
Summary: Kolmogorov-Arnold Mixtures of Experts LSTM
Author: Rémi Genet
Requires-Python: >=3.9,<4.0
Classifier: Programming Language :: Python :: 3
Classifier: Programming Language :: Python :: 3.9
Classifier: Programming Language :: Python :: 3.10
Classifier: Programming Language :: Python :: 3.11
Classifier: Programming Language :: Python :: 3.12
Requires-Dist: numpy (>=1.2,<2)
Requires-Dist: tensorflow (>=2.8,<3)
